[{"DeviceName": "Lenovo Vibe K4 Note", "Brand": "Lenovo", "technology": "GSM / HSPA / LTE", "gprs": "Yes", "edge": "Yes", "announced": "2016, January", "status": "Available. Released 2016, January", "dimensions": "153.6 x 76.5 x 9.2 mm (6.05 x 3.01 x 0.36 in)", "weight": "158 g (5.57 oz)", "sim": "Dual SIM (Micro-SIM, dual stand-by)", "type": "IPS LCD capacitive touchscreen, 16M colors", "size": "5.5 inches (~71.0% screen-to-body ratio)", "resolution": "1080 x 1920 pixels (~401 ppi pixel density)", "card_slot": "microSD, up to 128 GB", "alert_types": "Vibration; MP3, WAV ringtones", "loudspeaker_": "Yes, with stereo speakers", "sound_c": "- Dolby Atmos sound", "wlan": "Wi-Fi 802.11 a/b/g/n/ac, Wi-Fi Direct, hotspot", "bluetooth": "v4.0, A2DP, LE", "gps": "Yes, with A-GPS", "radio": "FM radio", "usb": "microUSB v2.0", "messaging": "SMS(threaded view), MMS, Email, Push Mail, IM", "browser": "HTML5", "java": "No", "features_c": "- Active noise cancellation with dedicated mic\r\n  - MP4/H.264 player\r\n  - MP3/WAV/eAAC+/FLAC player\r\n  - Photo/video editor\r\n  - Document viewer", "battery_c": "Non-removable Li-Po 3300 mAh battery", "stand_by": "Up to 265 h (3G)", "talk_time": "Up to 23 h (2G) / Up to 22 h (3G)", "colors": "Black", "sensors": "Fingerprint, accelerometer, gyro, proximity, compass", "cpu": "Octa-core 1.3 GHz Cortex-A53", "internal": "16 GB, 3 GB RAM - A7010 a48\r\n8/16/32 GB, 2 GB RAM - A7010", "os": "Android OS, v5.1 (Lollipop)", "primary_": "13 MP, f/2.2, phase detection autofocus, dual-LED (dual tone) flash", "video": "1080p@30fps", "secondary": "5 MP", "speed": "HSPA, LTE Cat4 150/50 Mbps", "network_c": "LTE band 1(2100), 3(1800), 5(850), 7(2600), 8(900), 20(800), 40(2300), 41(2500) - A7010 a48", "chipset": "Mediatek MT6753", "features": "Geo-tagging, touch focus, face detection, HDR, panorama", "protection": "Corning Gorilla Glass 3", "gpu": "Mali-T720MP3", "multitouch": "Yes", "nfc": "Yes", "_2g_bands": "GSM 850 / 900 / 1800 / 1900 - SIM 1 & SIM 2", "_3_5mm_jack_": "Yes", "_3g_bands": "HSDPA 850 / 900 / 1900 / 2100 ", "_4g_bands": "LTE band 1(2100), 3(1800), 5(850), 7(2600), 8(900), 20(800) - A7010"}]